comap/__init__.py
comap/api.py
comap/api_async.py
comap/constants.py
comap-0.3.2.dist-info/LICENSE
comap-0.3.2.dist-info/METADATA
comap-0.3.2.dist-info/WHEEL
comap-0.3.2.dist-info/top_level.txt
comap-0.3.2.dist-info/RECORD
