Metadata-Version: 2.1
Name: comap
Version: 0.3.2
Summary: Allows easy automation of WebSupervisor tasks, such as downloading and analyzing data
Home-page: https://github.com/bruxy70/ComAp
Author: Václav Chaloupka
Author-email: vasek.chaloupka@hotmail.com
License: MIT
Classifier: Programming Language :: Python
Classifier: Programming Language :: Python :: 3
Classifier: Programming Language :: Python :: 3.11
Classifier: License :: OSI Approved :: MIT License
Classifier: Operating System :: OS Independent
Classifier: Intended Audience :: Developers
Requires-Python: >=3.11.0
License-File: LICENSE
Requires-Dist: asyncio
Requires-Dist: aiohttp
Requires-Dist: async-timeout
Requires-Dist: requests
Requires-Dist: aiofiles
Requires-Dist: timestring
